Metadata-Version: 2.1
Name: easyglue
Version: 0.0.9
Summary: Glue DynamicFrame syntax closer to DataFrames
Home-page: UNKNOWN
Author: Albert Quiroga
Author-email: albertquirogabertolin@gmail.com
License: UNKNOWN
Platform: UNKNOWN
Requires-Python: >=3.0
